odoo8_addon_sale_last_price_info-8.0.1.0.0.99.dev19-py3.8-nspkg.pth
odoo_addons/sale_last_price_info/README.rst
odoo_addons/sale_last_price_info/__init__.py
odoo_addons/sale_last_price_info/__openerp__.py
odoo_addons/sale_last_price_info/i18n/ca.po
odoo_addons/sale_last_price_info/i18n/de.po
odoo_addons/sale_last_price_info/i18n/el_GR.po
odoo_addons/sale_last_price_info/i18n/es.po
odoo_addons/sale_last_price_info/i18n/es_ES.po
odoo_addons/sale_last_price_info/i18n/fi.po
odoo_addons/sale_last_price_info/i18n/fr.po
odoo_addons/sale_last_price_info/i18n/fr_CH.po
odoo_addons/sale_last_price_info/i18n/fr_FR.po
odoo_addons/sale_last_price_info/i18n/gl.po
odoo_addons/sale_last_price_info/i18n/hr.po
odoo_addons/sale_last_price_info/i18n/hr_HR.po
odoo_addons/sale_last_price_info/i18n/it.po
odoo_addons/sale_last_price_info/i18n/nl.po
odoo_addons/sale_last_price_info/i18n/nl_NL.po
odoo_addons/sale_last_price_info/i18n/pt.po
odoo_addons/sale_last_price_info/i18n/pt_BR.po
odoo_addons/sale_last_price_info/i18n/ro.po
odoo_addons/sale_last_price_info/i18n/ru.po
odoo_addons/sale_last_price_info/i18n/sale_last_price_info.pot
odoo_addons/sale_last_price_info/i18n/sk.po
odoo_addons/sale_last_price_info/i18n/sl.po
odoo_addons/sale_last_price_info/i18n/tr.po
odoo_addons/sale_last_price_info/i18n/tr_TR.po
odoo_addons/sale_last_price_info/i18n/vi_VN.po
odoo_addons/sale_last_price_info/i18n/zh_CN.po
odoo_addons/sale_last_price_info/models/__init__.py
odoo_addons/sale_last_price_info/models/product.py
odoo_addons/sale_last_price_info/static/description/icon.png
odoo_addons/sale_last_price_info/tests/__init__.py
odoo_addons/sale_last_price_info/tests/test_sale_last_price_info.py
odoo_addons/sale_last_price_info/views/product_view.xml
odoo8_addon_sale_last_price_info-8.0.1.0.0.99.dev19.dist-info/METADATA
odoo8_addon_sale_last_price_info-8.0.1.0.0.99.dev19.dist-info/WHEEL
odoo8_addon_sale_last_price_info-8.0.1.0.0.99.dev19.dist-info/namespace_packages.txt
odoo8_addon_sale_last_price_info-8.0.1.0.0.99.dev19.dist-info/top_level.txt
odoo8_addon_sale_last_price_info-8.0.1.0.0.99.dev19.dist-info/RECORD
